<?xml version="1.0" encoding="utf-8"?>
<odoo>
    <data>
        
        <record id="inherit_stock_inventory_form_view" model="ir.ui.view">
            <field name="name">stock.inventory.form.view</field>
            <field name="model">stock.inventory</field>
            <field name="inherit_id" ref="stock.view_inventory_form"/>
            <field name="arch" type="xml">
				<button name='action_done' position="before">
					<button name="%(import.import_stock_wizard_action)d" type="action" string="Update Stock" class="oe_highlight"/>
				</button>				
			</field>
		</record>
        
     <record id="import_stock_wizard_form" model="ir.ui.view">
            <field name="name">import.stock.wizard.form</field>
            <field name="model">stock.import</field>
            <field name="arch" type="xml">
                <form string="Import a csv file">
                    <group name="main">
                        <field name="csv_file" />
                    </group>
                    <footer>
                        <button name="import_csv" type="object" string="Import" class="oe_highlight"/>
                        <button special="cancel" string="Cancel"/>
                    </footer>
                </form>
            </field>
        </record>   
       
        <record id="import_stock_wizard_action" model="ir.actions.act_window">
            <field name="name">Import a csv file</field>
            <field name="res_model">stock.import</field>
            <field name="view_mode">form</field>
            <field name="target">new</field>
        </record>
       
<!--
        <menuitem id="import_stock_wizard_menu"
                  name="Import Stock"
                  parent="stock.menu_warehouse_report"
                  action="import_stock_wizard_action"
                  sequence="1" /> 
-->

					
	</data>
</odoo>
